[
  {
    "link": "https://dawaai.pk/medicine/Herbessor-Tablet30-40.html",
    "name": "Herbesser"
  },
  {
    "link": "https://dawaai.pk/medicine/Herbessor-Tablet60-41.html",
    "name": "Herbesser"
  },
  {
    "link": "https://dawaai.pk/medicine/HerbessorSrCap-180-42.html",
    "name": "Herbesser"
  },
  {
    "link": "https://dawaai.pk/medicine/HerbessorSRCap-90-43.html",
    "name": "Herbesser"
  },
  {
    "link": "https://dawaai.pk/medicine/hcq-200-294.html",
    "name": "HCQ"
  },
  {
    "link": "https://dawaai.pk/medicine/helezol-20mg-350.html",
    "name": "Helezol"
  },
  {
    "link": "https://dawaai.pk/medicine/hitone-cream-424.html",
    "name": "Hitone Whitening Cream 30 gm / 1.05 Fl.oz Pack"
  },
  {
    "link": "https://dawaai.pk/medicine/higrow-480.html",
    "name": "Higrow"
  },
  {
    "link": "https://dawaai.pk/medicine/hytrin-1mg-645.html",
    "name": "Hytrin 1mg"
  },
  {
    "link": "https://dawaai.pk/medicine/hytrin-1mg-646.html",
    "name": "Hytrin 2mg"
  },
  {
    "link": "https://dawaai.pk/medicine/hytrin-1mg-647.html",
    "name": "Hytrin 5mg"
  },
  {
    "link": "https://dawaai.pk/medicine/hepa-merz-granules-657.html",
    "name": "Hepa Merz"
  },
  {
    "link": "https://dawaai.pk/medicine/hepa-merz-syrup-658.html",
    "name": "Hepa Merz"
  },
  {
    "link": "https://dawaai.pk/medicine/hydrozole-cream-5403.html",
    "name": "Hydrozole Cream"
  },
  {
    "link": "https://dawaai.pk/medicine/heamocare-ferplex-120-ml-syrup-6500.html",
    "name": "Heamocare 120ml"
  },
  {
    "link": "https://dawaai.pk/medicine/hicap-plus-tab-6513.html",
    "name": "Hicap Plus"
  },
  {
    "link": "https://dawaai.pk/medicine/hivate-20ml-lotion-6532.html",
    "name": "Hivate Lotion 30ml"
  },
  {
    "link": "https://dawaai.pk/medicine/hivate-nasal-spray-50mcg-6533.html",
    "name": "Hivate Nasal Spray"
  },
  {
    "link": "https://dawaai.pk/medicine/hmg-massone-gonadotrophin-75iu-injection-6537.html",
    "name": "HMG MASSONE ( Gonadotrophin ) 75IU INJECTION"
  },
  {
    "link": "https://dawaai.pk/medicine/hyderquin-plus-cream-6552.html",
    "name": "Hyderquin Plus"
  },
  {
    "link": "https://dawaai.pk/medicine/heamocare-plus-tab-14s-9458.html",
    "name": "Heamocare Plus"
  },
  {
    "link": "https://dawaai.pk/medicine/hylo-eye-drop-02-5ml-9474.html",
    "name": "Hylo"
  },
  {
    "link": "https://dawaai.pk/medicine/amson-hyzonat-inj-100mg-10025.html",
    "name": "Hyzonate"
  },
  {
    "link": "https://dawaai.pk/medicine/hart-5-10907.html",
    "name": "Hart"
  },
  {
    "link": "https://dawaai.pk/medicine/hilin-12639.html",
    "name": "Hilin"
  },
  {
    "link": "https://dawaai.pk/medicine/hilin-1-12640.html",
    "name": "Hilin"
  },
  {
    "link": "https://dawaai.pk/medicine/hilin-2-12641.html",
    "name": "Hilin"
  },
  {
    "link": "https://dawaai.pk/medicine/hilin-3-12642.html",
    "name": "Hilin"
  },
  {
    "link": "https://dawaai.pk/medicine/hilin-4-12643.html",
    "name": "Hilin"
  },
  {
    "link": "https://dawaai.pk/medicine/hitop-12691.html",
    "name": "Hitop"
  },
  {
    "link": "https://dawaai.pk/medicine/hitop-1-12692.html",
    "name": "Hitop"
  },
  {
    "link": "https://dawaai.pk/medicine/hitop-2-12693.html",
    "name": "Hitop"
  },
  {
    "link": "https://dawaai.pk/medicine/hiloric-1-13428.html",
    "name": "Hiloric"
  },
  {
    "link": "https://dawaai.pk/medicine/histanil-d-17510.html",
    "name": "Histanil -D"
  },
  {
    "link": "https://dawaai.pk/medicine/hastin-17573.html",
    "name": "Hastin"
  },
  {
    "link": "https://dawaai.pk/medicine/hiflucan-19404.html",
    "name": "Hiflucan"
  },
  {
    "link": "https://dawaai.pk/medicine/histadine-2-20466.html",
    "name": "Histadine"
  },
  {
    "link": "https://dawaai.pk/medicine/histanil-2-20471.html",
    "name": "Histanil"
  },
  {
    "link": "https://dawaai.pk/medicine/humalog-lispro-20822.html",
    "name": "Humalog Lispro"
  },
  {
    "link": "https://dawaai.pk/medicine/humalog-lispro-1-20823.html",
    "name": "Humalog Lispro"
  },
  {
    "link": "https://dawaai.pk/medicine/humalog-lispro-2-20824.html",
    "name": "Humalog Lispro"
  },
  {
    "link": "https://dawaai.pk/medicine/humalog-mix-20825.html",
    "name": "Humalog Mix  25"
  },
  {
    "link": "https://dawaai.pk/medicine/humalog-mix-2-20827.html",
    "name": "Humalog Mix 50"
  },
  {
    "link": "https://dawaai.pk/medicine/hapicit-20-mg-23673.html",
    "name": "Hapicit"
  },
  {
    "link": "https://dawaai.pk/medicine/hilyte-r-23784.html",
    "name": "Hilyte-R"
  },
  {
    "link": "https://dawaai.pk/medicine/hiclor-24697.html",
    "name": "Hiclor"
  },
  {
    "link": "https://dawaai.pk/medicine/hiclor-1-24698.html",
    "name": "Hiclor"
  },
  {
    "link": "https://dawaai.pk/medicine/hiclor-3-24700.html",
    "name": "Hiclor"
  },
  {
    "link": "https://dawaai.pk/medicine/helicef-24962.html",
    "name": "Helicef"
  },
  {
    "link": "https://dawaai.pk/medicine/helicef-2-24964.html",
    "name": "Helicef"
  },
  {
    "link": "https://dawaai.pk/medicine/hizone-2-27188.html",
    "name": "Hizone"
  },
  {
    "link": "https://dawaai.pk/medicine/hizone-3-27189.html",
    "name": "Hizone"
  },
  {
    "link": "https://dawaai.pk/medicine/hitra-550-mg-28184.html",
    "name": "Hitra 550 mg"
  },
  {
    "link": "https://dawaai.pk/medicine/hifen-x-1-34005.html",
    "name": "Hifen-X"
  },
  {
    "link": "https://dawaai.pk/medicine/hifen-x-2-34006.html",
    "name": "Hifen-X"
  },
  {
    "link": "https://dawaai.pk/medicine/humapen-ergo-ii-34899.html",
    "name": "Humapen Ergo II"
  },
  {
    "link": "https://dawaai.pk/medicine/hadensa-ointment-25-gm-35562.html",
    "name": "Hadesa Comfort"
  },
  {
    "link": "https://dawaai.pk/medicine/havrix-1-36418.html",
    "name": "Havrix"
  },
  {
    "link": "https://dawaai.pk/medicine/high-c-36773.html",
    "name": "High-C 1000"
  },
  {
    "link": "https://dawaai.pk/medicine/hyseke-sol-2-60ml-37035.html",
    "name": "Hyseke Sol"
  },
  {
    "link": "https://dawaai.pk/medicine/hyzonate-250mg-37265.html",
    "name": "Hyzonate"
  },
  {
    "link": "https://dawaai.pk/medicine/hyzonate-500mg-1-37267.html",
    "name": "Hyzonate"
  },
  {
    "link": "https://dawaai.pk/medicine/humalog-mix-25-kwikpen-inj-100uml-5pfpx3ml-37491.html",
    "name": "Humalog Mix 25 Kwikpen "
  },
  {
    "link": "https://dawaai.pk/medicine/hepa-merz-37860.html",
    "name": "Hepa-Merz"
  },
  {
    "link": "https://dawaai.pk/medicine/heptocam-syrup-120ml-37979.html",
    "name": "Heptocam"
  },
  {
    "link": "https://dawaai.pk/medicine/hi-lacta-38084.html",
    "name": "Hi-Lacta"
  },
  {
    "link": "https://dawaai.pk/medicine/hepatovit-1-38088.html",
    "name": "Hepatovit"
  },
  {
    "link": "https://dawaai.pk/medicine/hilgas-syrup-38094.html",
    "name": "Hilgas Syrup"
  },
  {
    "link": "https://dawaai.pk/medicine/hapicit-e-10mg-2-38268.html",
    "name": "Hapicit-E"
  },
  {
    "link": "https://dawaai.pk/medicine/hipro-250mg-38322.html",
    "name": "Hipro"
  },
  {
    "link": "https://dawaai.pk/medicine/hapibar-38395.html",
    "name": "Hapibar"
  },
  {
    "link": "https://dawaai.pk/medicine/haemaccel-500ml-38806.html",
    "name": "Haemaccel 500ml"
  },
  {
    "link": "https://dawaai.pk/medicine/hidrasec-39176.html",
    "name": "Hidrasec"
  },
  {
    "link": "https://dawaai.pk/medicine/hivate-41026.html",
    "name": "Hivate"
  },
  {
    "link": "https://dawaai.pk/medicine/hair-max-2-minoxidil-43293.html",
    "name": "Hair Max 2% Minoxidil"
  },
  {
    "link": "https://dawaai.pk/medicine/hi-paradant-75g-43673.html",
    "name": "Hi-Paradent 75g"
  },
  {
    "link": "https://dawaai.pk/medicine/-46903.html",
    "name": "Humalog Mix 50 - "
  },
  {
    "link": "https://dawaai.pk/medicine/-47030.html",
    "name": "Histalis"
  },
  {
    "link": "https://dawaai.pk/medicine/-47031.html",
    "name": "Histalis"
  },
  {
    "link": "https://dawaai.pk/medicine/hapicite-e-20-mg-tablets-1-x-10s-pack-47424.html",
    "name": "Hapicite-E"
  },
  {
    "link": "https://dawaai.pk/medicine/hivate-50-mg-nasal-spray-60-doses-pack-47613.html",
    "name": "Hivate"
  },
  {
    "link": "https://dawaai.pk/medicine/hiflox-250-mg-tablets-1-x-10s-pack-47859.html",
    "name": "Hiflox"
  },
  {
    "link": "https://dawaai.pk/medicine/hiflox-500-mg-tablets-1-x-10s-pack-47860.html",
    "name": "Hiflox"
  },
  {
    "link": "https://dawaai.pk/medicine/hitica-90-mg-tablet-1-x-10s-pack-47982.html",
    "name": "Hitica"
  },
  {
    "link": "https://dawaai.pk/medicine/hitica-60-mg-tablet-1-x-10s-pack-47983.html",
    "name": "Hitica"
  },
  {
    "link": "https://dawaai.pk/medicine/helixa-10-mg-tablets-1-x-10s-pack-48057.html",
    "name": "Helixa"
  },
  {
    "link": "https://dawaai.pk/medicine/hairfin-1-mg-tablets-3-x-10s-pack-49087.html",
    "name": "Hairfin"
  },
  {
    "link": "https://dawaai.pk/medicine/hapibar-60-mg-capsules-1-x-14s-pack-49249.html",
    "name": "Hapibar"
  },
  {
    "link": "https://dawaai.pk/medicine/hifolic-400-mg-tablet-3-x-10s-pack-50331.html",
    "name": "Hifolic 400 mg "
  },
  {
    "link": "https://dawaai.pk/medicine/hifolic-300-mg-tablet-3-x-10s-pack-50332.html",
    "name": "Hifolic 300 mg "
  },
  {
    "link": "https://dawaai.pk/medicine/hifolic-600-mg-tablet-3-x10s-pack-50333.html",
    "name": "Hifolic 600 mg "
  },
  {
    "link": "https://dawaai.pk/medicine/hinubon-tablet-2-x-10s-pack-50353.html",
    "name": "Hinubon "
  },
  {
    "link": "https://dawaai.pk/medicine/hydryllin-118.html",
    "name": "Hydryllin"
  },
  {
    "link": "https://dawaai.pk/medicine/hydryllin-dm-325.html",
    "name": "Hydryllin Dm"
  },
  {
    "link": "https://dawaai.pk/medicine/hydrocortisone--1664.html",
    "name": "Hydrocortisone 10g"
  },
  {
    "link": "https://dawaai.pk/medicine/hydrogen-peroxide-110-ml-1946.html",
    "name": "Hydrogen Peroxide - 110 Ml"
  },
  {
    "link": "https://dawaai.pk/medicine/healit-skin-ointment-5399.html",
    "name": "Healit Skin Ointment"
  },
  {
    "link": "https://dawaai.pk/medicine/hart-3-10905.html",
    "name": "Hart"
  },
  {
    "link": "https://dawaai.pk/medicine/hart-4-10906.html",
    "name": "Hart"
  },
  {
    "link": "https://dawaai.pk/medicine/hiflone-1-16453.html",
    "name": "Hiflone"
  },
  {
    "link": "https://dawaai.pk/medicine/histadine-1-20465.html",
    "name": "Histadine"
  },
  {
    "link": "https://dawaai.pk/medicine/hydrolite-23785.html",
    "name": "Hydro Lyte"
  },
  {
    "link": "https://dawaai.pk/medicine/hiclor-2-24699.html",
    "name": "Hiclor"
  },
  {
    "link": "https://dawaai.pk/medicine/helicef-1-24963.html",
    "name": "Helicef"
  },
  {
    "link": "https://dawaai.pk/medicine/hifen-x-34004.html",
    "name": "Hifen-X"
  },
  {
    "link": "https://dawaai.pk/medicine/histalyn-36665.html",
    "name": "Histalyn eye drop 5ml 2%"
  },
  {
    "link": "https://dawaai.pk/medicine/humulin-7030-inj-100iuml-5cartridgesx3ml-37506.html",
    "name": "Humulin 70/30"
  },
  {
    "link": "https://dawaai.pk/medicine/hydrocortisone-43234.html",
    "name": "Hydrocortisone 5g"
  },
  {
    "link": "https://dawaai.pk/medicine/humalog-342.html",
    "name": "Humalog Vial"
  },
  {
    "link": "https://dawaai.pk/medicine/hashmi-ispaghol-414.html",
    "name": "Hashmi Ispaghol Husk 100gm"
  },
  {
    "link": "https://dawaai.pk/medicine/hair-max-plus-5-466.html",
    "name": "Hair Max Plus 5%"
  },
  {
    "link": "https://dawaai.pk/medicine/heparin-injection-25000-units-935.html",
    "name": "Heparin Injection 25000 Units"
  },
  {
    "link": "https://dawaai.pk/medicine/hair-vit-capsules-30s-1499.html",
    "name": "Hair Vit Capsules 30s"
  },
  {
    "link": "https://dawaai.pk/medicine/herbo-natural-jariancare-powder-150g-2683.html",
    "name": "Herbo Natural Jariancare Powder"
  },
  {
    "link": "https://dawaai.pk/medicine/herbo-natural-premet-powder-150g-2684.html",
    "name": "Herbo Natural Premet Powder 150g"
  },
  {
    "link": "https://dawaai.pk/medicine/herbo-natural-fertilex-powder-capsules-for-males-2685.html",
    "name": "Herbo Natural Fertilex Powder For Males"
  },
  {
    "link": "https://dawaai.pk/medicine/herbo-natural-mega-pack-shaadi-course-2686.html",
    "name": "Herbo Natural Mega Pack - Shaadi Course"
  },
  {
    "link": "https://dawaai.pk/medicine/herbo-natural-mega-pack-lite-course-2687.html",
    "name": "Herbo Natural Mega Pack - Lite Course"
  },
  {
    "link": "https://dawaai.pk/medicine/herbo-natural-curve-grow-2689.html",
    "name": "Herbo Natural Curve Grow"
  },
  {
    "link": "https://dawaai.pk/medicine/herbo-natural-ginkgo-biloba-capsules-2691.html",
    "name": "Herbo Natural Ginkgo Biloba Capsules"
  },
  {
    "link": "https://dawaai.pk/medicine/herbo-natural-ginseng-capsules-2692.html",
    "name": "Herbo Natural Ginseng Capsules"
  },
  {
    "link": "https://dawaai.pk/medicine/herbo-natural-ashwagandha-capsules-2693.html",
    "name": "Herbo Natural Ashwagandha Capsules"
  },
  {
    "link": "https://dawaai.pk/medicine/herbo-natural-morman-oil-2694.html",
    "name": "Herbo Natural Morman Oil"
  },
  {
    "link": "https://dawaai.pk/medicine/herbo-natural-stovuline-capsules-2695.html",
    "name": "Herbo Natural Stovuline Capsules"
  },
  {
    "link": "https://dawaai.pk/medicine/herbo-natural-rovuline-capsules-2697.html",
    "name": "Herbo Natural Rovuline Capsules"
  },
  {
    "link": "https://dawaai.pk/medicine/herbo-natural-maca-root-powder-2698.html",
    "name": "Herbo Natural Maca Root Powder"
  },
  {
    "link": "https://dawaai.pk/medicine/herbo-natural-leko-care-powder-2700.html",
    "name": "Herbo Natural Leko Care Powder"
  },
  {
    "link": "https://dawaai.pk/medicine/herbo-natural-liver-care-capsules-milk-thistle-2701.html",
    "name": "Herbo Natural Liver Care Capsules Milk Thistle"
  },
  {
    "link": "https://dawaai.pk/medicine/herbo-natural-liver-care-capsules-hepatitis-b-2702.html",
    "name": "Herbo Natural Liver Care Capsules Hepatitis B"
  },
  {
    "link": "https://dawaai.pk/medicine/herbo-natural-hemorex-capsules-2704.html",
    "name": "Herbo Natural Hemorex Capsules"
  },
  {
    "link": "https://dawaai.pk/medicine/herbo-natural-lactovit-powder-for-females-150g-2709.html",
    "name": "Herbo Natural Lactovit Powder For Females 150g"
  },
  {
    "link": "https://dawaai.pk/medicine/hivate-cream-01-5400.html",
    "name": "Hivate Cream 0.1%"
  },
  {
    "link": "https://dawaai.pk/medicine/clariderm-hydroquinone-2-10-g-cream-5920.html",
    "name": "Hydroquinone 2 ounce"
  },
  {
    "link": "https://dawaai.pk/medicine/hairfin-1mg-tab-6490.html",
    "name": "Hairfin"
  },
  {
    "link": "https://dawaai.pk/medicine/histazolin-eye-drop-cromogylcate-drops-6531.html",
    "name": "Histazolin"
  },
  {
    "link": "https://dawaai.pk/medicine/hyporide-2-10945.html",
    "name": "Hyporide"
  },
  {
    "link": "https://dawaai.pk/medicine/hyprol-1-10947.html",
    "name": "Hyprol"
  },
  {
    "link": "https://dawaai.pk/medicine/higesic-12002.html",
    "name": "Higesic"
  },
  {
    "link": "https://dawaai.pk/medicine/hi-gab-1-12420.html",
    "name": "Hi-Gab"
  },
  {
    "link": "https://dawaai.pk/medicine/heligesic-12936.html",
    "name": "Heligesic"
  },
  {
    "link": "https://dawaai.pk/medicine/hypeernorm-13165.html",
    "name": "Hypeernorm"
  },
  {
    "link": "https://dawaai.pk/medicine/hyzaar-13387.html",
    "name": "Hyzaar"
  },
  {
    "link": "https://dawaai.pk/medicine/hiloric-13427.html",
    "name": "Hiloric"
  },
  {
    "link": "https://dawaai.pk/medicine/hatide-13545.html",
    "name": "Hatide"
  },
  {
    "link": "https://dawaai.pk/medicine/hyocit-1-13601.html",
    "name": "Hyocit"
  },
  {
    "link": "https://dawaai.pk/medicine/humatrope-13612.html",
    "name": "Humatrope"
  },
  {
    "link": "https://dawaai.pk/medicine/hypergen-14403.html",
    "name": "Hypergen"
  },
  {
    "link": "https://dawaai.pk/medicine/hazid-14476.html",
    "name": "Hazid"
  },
  {
    "link": "https://dawaai.pk/medicine/hith-14477.html",
    "name": "Hith"
  },
  {
    "link": "https://dawaai.pk/medicine/hyzitek-14478.html",
    "name": "Hyzitek"
  },
  {
    "link": "https://dawaai.pk/medicine/hyzitek-1-14479.html",
    "name": "Hyzitek"
  },
  {
    "link": "https://dawaai.pk/medicine/hyzitek-2-14480.html",
    "name": "Hyzitek"
  },
  {
    "link": "https://dawaai.pk/medicine/hyzith-14481.html",
    "name": "Hyzith"
  },
  {
    "link": "https://dawaai.pk/medicine/healcin-14857.html",
    "name": "Healcin"
  },
  {
    "link": "https://dawaai.pk/medicine/healcin-1-14858.html",
    "name": "Healcin"
  },
  {
    "link": "https://dawaai.pk/medicine/homycin-14859.html",
    "name": "Homycin"
  },
  {
    "link": "https://dawaai.pk/medicine/h-done-14924.html",
    "name": "H-Done"
  },
  {
    "link": "https://dawaai.pk/medicine/hemax-15122.html",
    "name": "Hemax"
  },
  {
    "link": "https://dawaai.pk/medicine/hemax-1-15123.html",
    "name": "Hemax"
  },
  {
    "link": "https://dawaai.pk/medicine/hemax-3-15125.html",
    "name": "Hemax"
  },
  {
    "link": "https://dawaai.pk/medicine/healso-15377.html",
    "name": "Healso"
  },
  {
    "link": "https://dawaai.pk/medicine/hemso-15378.html",
    "name": "Hemso"
  },
  {
    "link": "https://dawaai.pk/medicine/hemso-1-15379.html",
    "name": "Hemso"
  },
  {
    "link": "https://dawaai.pk/medicine/hicot-3-16600.html",
    "name": "Hicot"
  },
  {
    "link": "https://dawaai.pk/medicine/hodacin-1-17088.html",
    "name": "Hodacin"
  },
  {
    "link": "https://dawaai.pk/medicine/histamol-2-17445.html",
    "name": "Histamol"
  },
  {
    "link": "https://dawaai.pk/medicine/histamol-3-17446.html",
    "name": "Histamol"
  },
  {
    "link": "https://dawaai.pk/medicine/histaset-1-17739.html",
    "name": "Histaset"
  },
  {
    "link": "https://dawaai.pk/medicine/hydrolate-17767.html",
    "name": "Hydrolate"
  },
  {
    "link": "https://dawaai.pk/medicine/hepbi-18470.html",
    "name": "Hepbi"
  },
  {
    "link": "https://dawaai.pk/medicine/hepiral-18471.html",
    "name": "Hepiral"
  },
  {
    "link": "https://dawaai.pk/medicine/hepovir-18472.html",
    "name": "Hepovir"
  },
  {
    "link": "https://dawaai.pk/medicine/hepsera-18473.html",
    "name": "Hepsera"
  },
  {
    "link": "https://dawaai.pk/medicine/healazin-1-18771.html",
    "name": "Healazin"
  },
  {
    "link": "https://dawaai.pk/medicine/heparin-inj-18926.html",
    "name": "Heparin Inj"
  },
  {
    "link": "https://dawaai.pk/medicine/heparin-18927.html",
    "name": "Heparin"
  },
  {
    "link": "https://dawaai.pk/medicine/heparin-inj-1-18928.html",
    "name": "Heparin Inj"
  },
  {
    "link": "https://dawaai.pk/medicine/hymex-18940.html",
    "name": "Hymex"
  },
  {
    "link": "https://dawaai.pk/medicine/hyo-plus-18950.html",
    "name": "Hyo-Plus"
  },
  {
    "link": "https://dawaai.pk/medicine/hepaferon-18958.html",
    "name": "Hepaferon"
  },
  {
    "link": "https://dawaai.pk/medicine/hiferon-18959.html",
    "name": "Hiferon"
  },
  {
    "link": "https://dawaai.pk/medicine/hiferon-1-18960.html",
    "name": "Hiferon"
  },
  {
    "link": "https://dawaai.pk/medicine/heberon-1-18983.html",
    "name": "Heberon"
  },
  {
    "link": "https://dawaai.pk/medicine/healac-19717.html",
    "name": "Healac"
  },
  {
    "link": "https://dawaai.pk/medicine/helilac-19718.html",
    "name": "Helilac"
  },
  {
    "link": "https://dawaai.pk/medicine/hepaid-19745.html",
    "name": "Hepaid"
  },
  {
    "link": "https://dawaai.pk/medicine/h2-zol-19780.html",
    "name": "H2-Zol"
  },
  {
    "link": "https://dawaai.pk/medicine/hilatan-19874.html",
    "name": "Hilatan"
  },
  {
    "link": "https://dawaai.pk/medicine/hamflox-19987.html",
    "name": "Hamflox"
  },
  {
    "link": "https://dawaai.pk/medicine/hamflox-1-19988.html",
    "name": "Hamflox"
  },
  {
    "link": "https://dawaai.pk/medicine/hector-19989.html",
    "name": "Hector"
  },
  {
    "link": "https://dawaai.pk/medicine/hector-1-19990.html",
    "name": "Hector"
  },
  {
    "link": "https://dawaai.pk/medicine/hisun-20798.html",
    "name": "Hisun"
  },
  {
    "link": "https://dawaai.pk/medicine/hisun-1-20799.html",
    "name": "Hisun"
  },
  {
    "link": "https://dawaai.pk/medicine/humalog-mix-1-20826.html",
    "name": "Humalog Mix"
  },
  {
    "link": "https://dawaai.pk/medicine/humalog-mix-3-20828.html",
    "name": "Humalog Mix 25"
  },
  {
    "link": "https://dawaai.pk/medicine/hartace-20995.html",
    "name": "Hartace"
  },
  {
    "link": "https://dawaai.pk/medicine/hartace-1-20996.html",
    "name": "Hartace"
  },
  {
    "link": "https://dawaai.pk/medicine/hartace-plus-21004.html",
    "name": "Hartace Plus"
  },
  {
    "link": "https://dawaai.pk/medicine/hiace-21016.html",
    "name": "Hiace"
  },
  {
    "link": "https://dawaai.pk/medicine/hiace-1-21017.html",
    "name": "Hiace"
  },
  {
    "link": "https://dawaai.pk/medicine/hiace-2-21018.html",
    "name": "Hiace"
  },
  {
    "link": "https://dawaai.pk/medicine/hyperace-21019.html",
    "name": "Hyperace"
  },
  {
    "link": "https://dawaai.pk/medicine/hyperace-1-21020.html",
    "name": "Hyperace"
  },
  {
    "link": "https://dawaai.pk/medicine/hepa-merz-syp-300mg5ml-120ml-21562.html",
    "name": "Hepa-Merz"
  },
  {
    "link": "https://dawaai.pk/medicine/herbesser-1-22632.html",
    "name": "Herbesser"
  },
  {
    "link": "https://dawaai.pk/medicine/hytorac-23860.html",
    "name": "Hytorac"
  },
  {
    "link": "https://dawaai.pk/medicine/hefmic-1-23940.html",
    "name": "Hefmic"
  },
  {
    "link": "https://dawaai.pk/medicine/hepmol-2-24264.html",
    "name": "Hepmol"
  },
  {
    "link": "https://dawaai.pk/medicine/hiclor-4-24701.html",
    "name": "Hiclor"
  },
  {
    "link": "https://dawaai.pk/medicine/heproxil-24965.html",
    "name": "Heproxil"
  },
  {
    "link": "https://dawaai.pk/medicine/heproxil-2-24967.html",
    "name": "Heproxil"
  },
  {
    "link": "https://dawaai.pk/medicine/hidrox-24968.html",
    "name": "Hidrox"
  },
  {
    "link": "https://dawaai.pk/medicine/hidrox-2-24970.html",
    "name": "Hidrox"
  },
  {
    "link": "https://dawaai.pk/medicine/hefixim-25496.html",
    "name": "Hefixim"
  },
  {
    "link": "https://dawaai.pk/medicine/hefixim-1-25497.html",
    "name": "Hefixim"
  },
  {
    "link": "https://dawaai.pk/medicine/hanpezone-25865.html",
    "name": "Hanpezone"
  },
  {
    "link": "https://dawaai.pk/medicine/hexime-26248.html",
    "name": "Hexime"
  },
  {
    "link": "https://dawaai.pk/medicine/hexime-1-26249.html",
    "name": "Hexime"
  },
  {
    "link": "https://dawaai.pk/medicine/hexime-3-26251.html",
    "name": "Hexime"
  },
  {
    "link": "https://dawaai.pk/medicine/hylaform-26252.html",
    "name": "Hylaform"
  },
  {
    "link": "https://dawaai.pk/medicine/hylaform-2-26254.html",
    "name": "Hylaform"
  },
  {
    "link": "https://dawaai.pk/medicine/hypertax-26255.html",
    "name": "Hypertax"
  },
  {
    "link": "https://dawaai.pk/medicine/hypertax-2-26257.html",
    "name": "Hypertax"
  },
  {
    "link": "https://dawaai.pk/medicine/haridone-26660.html",
    "name": "Haridone"
  },
  {
    "link": "https://dawaai.pk/medicine/haridone-2-26662.html",
    "name": "Haridone"
  },
  {
    "link": "https://dawaai.pk/medicine/hantox-3-27177.html",
    "name": "Hantox"
  },
  {
    "link": "https://dawaai.pk/medicine/hantox-5-27179.html",
    "name": "Hantox"
  },
  {
    "link": "https://dawaai.pk/medicine/hiway-2-27182.html",
    "name": "Hiway"
  },
  {
    "link": "https://dawaai.pk/medicine/hiway-3-27183.html",
    "name": "Hiway"
  },
  {
    "link": "https://dawaai.pk/medicine/hytrex-2-27192.html",
    "name": "Hytrex"
  },
  {
    "link": "https://dawaai.pk/medicine/hytrex-3-27193.html",
    "name": "Hytrex"
  },
  {
    "link": "https://dawaai.pk/medicine/hytrex-4-27194.html",
    "name": "Hytrex"
  },
  {
    "link": "https://dawaai.pk/medicine/heli-rox-27873.html",
    "name": "Heli-Rox"
  },
  {
    "link": "https://dawaai.pk/medicine/heli-rox-1-27874.html",
    "name": "Heli-Rox"
  },
  {
    "link": "https://dawaai.pk/medicine/heli-rox-3-27876.html",
    "name": "Heli-Rox"
  },
  {
    "link": "https://dawaai.pk/medicine/hancef-1-32797.html",
    "name": "Hancef"
  },
  {
    "link": "https://dawaai.pk/medicine/hancef-3-32799.html",
    "name": "Hancef"
  },
  {
    "link": "https://dawaai.pk/medicine/healcef-1-32801.html",
    "name": "Healcef"
  },
  {
    "link": "https://dawaai.pk/medicine/healcef-3-32803.html",
    "name": "Healcef"
  },
  {
    "link": "https://dawaai.pk/medicine/hicef-1-32805.html",
    "name": "Hicef"
  },
  {
    "link": "https://dawaai.pk/medicine/hicef-3-32807.html",
    "name": "Hicef"
  },
  {
    "link": "https://dawaai.pk/medicine/hilact-1-32809.html",
    "name": "Hilact"
  },
  {
    "link": "https://dawaai.pk/medicine/hilact-3-32811.html",
    "name": "Hilact"
  },
  {
    "link": "https://dawaai.pk/medicine/hecloron-l-34271.html",
    "name": "Hecloron-L"
  },
  {
    "link": "https://dawaai.pk/medicine/heumatic-34606.html",
    "name": "Heumatic"
  },
  {
    "link": "https://dawaai.pk/medicine/heumatic-1-34607.html",
    "name": "Heumatic"
  },
  {
    "link": "https://dawaai.pk/medicine/healsed-1-35072.html",
    "name": "Healsed"
  },
  {
    "link": "https://dawaai.pk/medicine/hyquine-35157.html",
    "name": "Hyquine"
  },
  {
    "link": "https://dawaai.pk/medicine/hizofen-35243.html",
    "name": "Hizofen"
  },
  {
    "link": "https://dawaai.pk/medicine/hizofen-1-35244.html",
    "name": "Hizofen"
  },
  {
    "link": "https://dawaai.pk/medicine/hizexin-35789.html",
    "name": "Hizexin"
  },
  {
    "link": "https://dawaai.pk/medicine/harricam-36198.html",
    "name": "Harricam"
  },
  {
    "link": "https://dawaai.pk/medicine/hyal-36255.html",
    "name": "Hyal"
  },
  {
    "link": "https://dawaai.pk/medicine/hyalgan-36256.html",
    "name": "Hyalgan"
  },
  {
    "link": "https://dawaai.pk/medicine/hyruan-36257.html",
    "name": "Hyruan"
  },
  {
    "link": "https://dawaai.pk/medicine/hyruan-1-36258.html",
    "name": "Hyruan"
  },
  {
    "link": "https://dawaai.pk/medicine/hyruan-2-36259.html",
    "name": "Hyruan"
  },
  {
    "link": "https://dawaai.pk/medicine/havrix-36417.html",
    "name": "Havrix"
  },
  {
    "link": "https://dawaai.pk/medicine/heberbiovac-36419.html",
    "name": "Heberbiovac"
  },
  {
    "link": "https://dawaai.pk/medicine/heberbiovac-1-36420.html",
    "name": "Heberbiovac"
  },
  {
    "link": "https://dawaai.pk/medicine/hep-vac-36421.html",
    "name": "Hep-Vac"
  },
  {
    "link": "https://dawaai.pk/medicine/hepatitis-b-vaccine-36422.html",
    "name": "Hepatitis B vaccine"
  },
  {
    "link": "https://dawaai.pk/medicine/hepatitis-b-vaccine-1-36423.html",
    "name": "Hepatitis B vaccine"
  },
  {
    "link": "https://dawaai.pk/medicine/hepatitis-b-vaccine-2-36424.html",
    "name": "Hepatitis B vaccine"
  },
  {
    "link": "https://dawaai.pk/medicine/hepatitis-b-vaccine-3-36425.html",
    "name": "Hepatitis B vaccine"
  },
  {
    "link": "https://dawaai.pk/medicine/hepatitis-b-vaccine-4-36426.html",
    "name": "Hepatitis B vaccine"
  },
  {
    "link": "https://dawaai.pk/medicine/hepatitis-b-vaccine-5-36427.html",
    "name": "Hepatitis B vaccine"
  },
  {
    "link": "https://dawaai.pk/medicine/hepatitis-b-vaccine-6-36428.html",
    "name": "Hepatitis B vaccine"
  },
  {
    "link": "https://dawaai.pk/medicine/hepatitis-b-vaccine-7-36429.html",
    "name": "Hepatitis B vaccine"
  },
  {
    "link": "https://dawaai.pk/medicine/hepavax-gene-36430.html",
    "name": "Hepavax-Gene"
  },
  {
    "link": "https://dawaai.pk/medicine/hepavax-gene-1-36431.html",
    "name": "Hepavax-Gene"
  },
  {
    "link": "https://dawaai.pk/medicine/heprovac-b-36432.html",
    "name": "Heprovac-B"
  },
  {
    "link": "https://dawaai.pk/medicine/heprovac-b-1-36433.html",
    "name": "Heprovac-B"
  },
  {
    "link": "https://dawaai.pk/medicine/hi-vax-b-36434.html",
    "name": "Hi-Vax B"
  },
  {
    "link": "https://dawaai.pk/medicine/hi-vax-b-1-36435.html",
    "name": "Hi-Vax B"
  },
  {
    "link": "https://dawaai.pk/medicine/hepatec-37172.html",
    "name": "Hepatect"
  },
  {
    "link": "https://dawaai.pk/medicine/hilvel-400mg100mg-37377.html",
    "name": "Hilvel"
  },
  {
    "link": "https://dawaai.pk/medicine/herbo-natural-fertilex-60-caps-38213.html",
    "name": "Herbo Natural Fertilex"
  },
  {
    "link": "https://dawaai.pk/medicine/higesic-2-38905.html",
    "name": "Higesic"
  },
  {
    "link": "https://dawaai.pk/medicine/hefmic-8-40248.html",
    "name": "Hefmic"
  },
  {
    "link": "https://dawaai.pk/medicine/hylin-42711.html",
    "name": "Hylin"
  },
  {
    "link": "https://dawaai.pk/medicine/hair-vit-hair-nails-30-soft-gels-43360.html",
    "name": "HAIR VIT HAIR & NAILS 30 SOFT GELS"
  },
  {
    "link": "https://dawaai.pk/medicine/hepaldi-tablet-400mg-44285.html",
    "name": "Hepaldi"
  },
  {
    "link": "https://dawaai.pk/medicine/hexaxim-45029.html",
    "name": "Hexaxim"
  },
  {
    "link": "https://dawaai.pk/medicine/herbal-olive-tin-soap-45090.html",
    "name": "Herbal Olive Tin Soap"
  },
  {
    "link": "https://dawaai.pk/medicine/havositol-sachets-10s-pack-50305.html",
    "name": "Havositol"
  },
  {
    "link": "https://dawaai.pk/medicine/happy-life-collection-condoms-mixed-3-in-1-38255.html",
    "name": "Happy Life Collection Condoms Mixed 3 in 1"
  },
  {
    "link": "https://dawaai.pk/medicine/hydryllin-sugar-free-324.html",
    "name": "Hydryllin Sugar Free"
  },
  {
    "link": "https://dawaai.pk/medicine/histamol-d-1-1876.html",
    "name": "Histamol-D"
  },
  {
    "link": "https://dawaai.pk/medicine/hadensa-forte-10gm-oint-6485.html",
    "name": "Hadensa Forte"
  },
  {
    "link": "https://dawaai.pk/medicine/hexidyl-trihexyphenidyl-hcl-2mg-tablet-6512.html",
    "name": "Hexidyl 2mg"
  },
  {
    "link": "https://dawaai.pk/medicine/hi-paradent-permethol-40-g-tooth-paste-6523.html",
    "name": "Hi-Paradent (Permethol) 40g Toothpaste"
  },
  {
    "link": "https://dawaai.pk/medicine/hyporide-3-10946.html",
    "name": "Hyporide"
  },
  {
    "link": "https://dawaai.pk/medicine/hycodine-11970.html",
    "name": "Hycodine"
  },
  {
    "link": "https://dawaai.pk/medicine/hi-gab-12419.html",
    "name": "Hi-Gab"
  },
  {
    "link": "https://dawaai.pk/medicine/hi-gab-2-12421.html",
    "name": "Hi-Gab"
  },
  {
    "link": "https://dawaai.pk/medicine/hiflexil-13082.html",
    "name": "Hiflexil"
  },
  {
    "link": "https://dawaai.pk/medicine/hedralka-13598.html",
    "name": "Hedralka"
  },
  {
    "link": "https://dawaai.pk/medicine/hised-13599.html",
    "name": "Hised"
  },
  {
    "link": "https://dawaai.pk/medicine/hyocit-13600.html",
    "name": "Hyocit"
  },
  {
    "link": "https://dawaai.pk/medicine/hht-13611.html",
    "name": "HHT"
  },
  {
    "link": "https://dawaai.pk/medicine/h-done-maleate-15042.html",
    "name": "H-Done Maleate"
  },
  {
    "link": "https://dawaai.pk/medicine/h-done-maleate-1-15043.html",
    "name": "H-Done Maleate"
  },
  {
    "link": "https://dawaai.pk/medicine/hemax-2-15124.html",
    "name": "Hemax"
  },
  {
    "link": "https://dawaai.pk/medicine/hemax-4-15126.html",
    "name": "Hemax"
  },
  {
    "link": "https://dawaai.pk/medicine/hydrate-15828.html",
    "name": "Hydrate"
  },
  {
    "link": "https://dawaai.pk/medicine/helipred-1-16473.html",
    "name": "Helipred"
  },
  {
    "link": "https://dawaai.pk/medicine/hicot-2-16599.html",
    "name": "Hicot"
  },
  {
    "link": "https://dawaai.pk/medicine/hydrinate-2-16829.html",
    "name": "Hydrinate"
  },
  {
    "link": "https://dawaai.pk/medicine/hydrinate-3-16830.html",
    "name": "Hydrinate"
  },
  {
    "link": "https://dawaai.pk/medicine/histagic-17440.html",
    "name": "Histagic"
  },
  {
    "link": "https://dawaai.pk/medicine/histanol-17441.html",
    "name": "Histanol"
  },
  {
    "link": "https://dawaai.pk/medicine/histanol-1-17442.html",
    "name": "Histanol"
  },
  {
    "link": "https://dawaai.pk/medicine/histamol-17443.html",
    "name": "Histamol"
  },
  {
    "link": "https://dawaai.pk/medicine/histamol-1-17444.html",
    "name": "Histamol"
  },
  {
    "link": "https://dawaai.pk/medicine/histom-17447.html",
    "name": "Histom"
  },
  {
    "link": "https://dawaai.pk/medicine/histosyn-17448.html",
    "name": "Histosyn"
  },
  {
    "link": "https://dawaai.pk/medicine/hanstine-17572.html",
    "name": "Hanstine"
  },
  {
    "link": "https://dawaai.pk/medicine/hibastin-17574.html",
    "name": "Hibastin"
  },
  {
    "link": "https://dawaai.pk/medicine/hotin-17575.html",
    "name": "Hotin"
  },
  {
    "link": "https://dawaai.pk/medicine/helvin-17737.html",
    "name": "Helvin"
  },
  {
    "link": "https://dawaai.pk/medicine/histaset-17738.html",
    "name": "Histaset"
  },
  {
    "link": "https://dawaai.pk/medicine/histasun-17740.html",
    "name": "Histasun"
  },
  {
    "link": "https://dawaai.pk/medicine/histasun-1-17741.html",
    "name": "Histasun"
  },
  {
    "link": "https://dawaai.pk/medicine/healazin-18770.html",
    "name": "Healazin"
  },
  {
    "link": "https://dawaai.pk/medicine/hetrizine-18772.html",
    "name": "Hetrizine"
  },
  {
    "link": "https://dawaai.pk/medicine/hismatec-18773.html",
    "name": "Hismatec"
  },
  {
    "link": "https://dawaai.pk/medicine/histant-18774.html",
    "name": "Histant"
  },
  {
    "link": "https://dawaai.pk/medicine/histex-18775.html",
    "name": "Histex"
  },
  {
    "link": "https://dawaai.pk/medicine/histex-1-18776.html",
    "name": "Histex"
  },
  {
    "link": "https://dawaai.pk/medicine/hizene-18777.html",
    "name": "Hizene"
  },
  {
    "link": "https://dawaai.pk/medicine/hozin-18778.html",
    "name": "Hozin"
  },
  {
    "link": "https://dawaai.pk/medicine/heparinol-18930.html",
    "name": "Heparinol"
  },
  {
    "link": "https://dawaai.pk/medicine/heparinol-1-18931.html",
    "name": "Heparinol"
  },
  {
    "link": "https://dawaai.pk/medicine/hyomide-18941.html",
    "name": "Hyomide"
  },
  {
    "link": "https://dawaai.pk/medicine/hyopen-plain-18942.html",
    "name": "Hyopen Plain"
  },
  {
    "link": "https://dawaai.pk/medicine/hyoscine-plus-18943.html",
    "name": "Hyoscine Plus"
  },
  {
    "link": "https://dawaai.pk/medicine/hyosgen-18944.html",
    "name": "Hyosgen"
  },
  {
    "link": "https://dawaai.pk/medicine/hifluzole-19405.html",
    "name": "Hifluzole"
  },
  {
    "link": "https://dawaai.pk/medicine/heisil-20461.html",
    "name": "Heisil"
  },
  {
    "link": "https://dawaai.pk/medicine/hico-od-20462.html",
    "name": "Hico-OD"
  },
  {
    "link": "https://dawaai.pk/medicine/hisrol-20463.html",
    "name": "Hisrol"
  },
  {
    "link": "https://dawaai.pk/medicine/histadine-20464.html",
    "name": "Histadine"
  },
  {
    "link": "https://dawaai.pk/medicine/histamac-20467.html",
    "name": "Histamac"
  },
  {
    "link": "https://dawaai.pk/medicine/histamac-1-20468.html",
    "name": "Histamac"
  },
  {
    "link": "https://dawaai.pk/medicine/histanil-20469.html",
    "name": "Histanil"
  },
  {
    "link": "https://dawaai.pk/medicine/histar-20472.html",
    "name": "Histar"
  },
  {
    "link": "https://dawaai.pk/medicine/histawel-20473.html",
    "name": "Histawel"
  },
  {
    "link": "https://dawaai.pk/medicine/historat-20474.html",
    "name": "Historat"
  },
  {
    "link": "https://dawaai.pk/medicine/humulin-7030-20829.html",
    "name": "Humulin 70/30"
  },
  {
    "link": "https://dawaai.pk/medicine/humulin-n-20831.html",
    "name": "Humulin-N"
  },
  {
    "link": "https://dawaai.pk/medicine/humulin-r-20832.html",
    "name": "Humulin-R"
  },
  {
    "link": "https://dawaai.pk/medicine/hipril-20917.html",
    "name": "Hipril"
  },
  {
    "link": "https://dawaai.pk/medicine/hipril-1-20918.html",
    "name": "Hipril"
  },
  {
    "link": "https://dawaai.pk/medicine/hefmic-23939.html",
    "name": "Hefmic"
  },
  {
    "link": "https://dawaai.pk/medicine/hepmol-24262.html",
    "name": "Hepmol"
  },
  {
    "link": "https://dawaai.pk/medicine/heproxil-1-24966.html",
    "name": "Heproxil"
  },
  {
    "link": "https://dawaai.pk/medicine/hidrox-1-24969.html",
    "name": "Hidrox"
  },
  {
    "link": "https://dawaai.pk/medicine/hexime-2-26250.html",
    "name": "Hexime"
  },
  {
    "link": "https://dawaai.pk/medicine/hylaform-1-26253.html",
    "name": "Hylaform"
  },
  {
    "link": "https://dawaai.pk/medicine/hypertax-1-26256.html",
    "name": "Hypertax"
  },
  {
    "link": "https://dawaai.pk/medicine/haridone-1-26661.html",
    "name": "Haridone"
  },
  {
    "link": "https://dawaai.pk/medicine/hantox-1-27175.html",
    "name": "Hantox"
  },
  {
    "link": "https://dawaai.pk/medicine/hiway-1-27181.html",
    "name": "Hiway"
  },
  {
    "link": "https://dawaai.pk/medicine/h2-rec-27562.html",
    "name": "H2-Rec"
  },
  {
    "link": "https://dawaai.pk/medicine/heli-rox-2-27875.html",
    "name": "Heli-Rox"
  },
  {
    "link": "https://dawaai.pk/medicine/hifal-32475.html",
    "name": "Hifal"
  },
  {
    "link": "https://dawaai.pk/medicine/hifal-1-32476.html",
    "name": "Hifal"
  },
  {
    "link": "https://dawaai.pk/medicine/hifal-2-32477.html",
    "name": "Hifal"
  },
  {
    "link": "https://dawaai.pk/medicine/hancef-32796.html",
    "name": "Hancef"
  },
  {
    "link": "https://dawaai.pk/medicine/hancef-2-32798.html",
    "name": "Hancef"
  },
  {
    "link": "https://dawaai.pk/medicine/healcef-32800.html",
    "name": "Healcef"
  },
  {
    "link": "https://dawaai.pk/medicine/healcef-2-32802.html",
    "name": "Healcef"
  },
  {
    "link": "https://dawaai.pk/medicine/hicef-32804.html",
    "name": "Hicef"
  },
  {
    "link": "https://dawaai.pk/medicine/hicef-2-32806.html",
    "name": "Hicef"
  },
  {
    "link": "https://dawaai.pk/medicine/hilact-32808.html",
    "name": "Hilact"
  },
  {
    "link": "https://dawaai.pk/medicine/hilact-2-32810.html",
    "name": "Hilact"
  },
  {
    "link": "https://dawaai.pk/medicine/hadansa-forte-cream-33593.html",
    "name": "Hadensa Forte Cream"
  },
  {
    "link": "https://dawaai.pk/medicine/heumatic-k-34137.html",
    "name": "Heumatic-K"
  },
  {
    "link": "https://dawaai.pk/medicine/hi-nil-34138.html",
    "name": "Hi-Nil"
  },
  {
    "link": "https://dawaai.pk/medicine/hondic-k-34139.html",
    "name": "Hondic-K"
  },
  {
    "link": "https://dawaai.pk/medicine/hecloron-l-1-34272.html",
    "name": "Hecloron-L"
  },
  {
    "link": "https://dawaai.pk/medicine/heclofen-34602.html",
    "name": "Heclofen"
  },
  {
    "link": "https://dawaai.pk/medicine/heclofen-1-34603.html",
    "name": "Heclofen"
  },
  {
    "link": "https://dawaai.pk/medicine/heltron-34604.html",
    "name": "Heltron"
  },
  {
    "link": "https://dawaai.pk/medicine/heltron-1-34605.html",
    "name": "Heltron"
  },
  {
    "link": "https://dawaai.pk/medicine/heumatic-2-34608.html",
    "name": "Heumatic"
  },
  {
    "link": "https://dawaai.pk/medicine/heumatic-3-34609.html",
    "name": "Heumatic"
  },
  {
    "link": "https://dawaai.pk/medicine/hi-nil-sr-34610.html",
    "name": "Hi-Nil SR"
  },
  {
    "link": "https://dawaai.pk/medicine/hondic-34611.html",
    "name": "Hondic"
  },
  {
    "link": "https://dawaai.pk/medicine/hebofen-35240.html",
    "name": "Hebofen"
  },
  {
    "link": "https://dawaai.pk/medicine/hibtol-35241.html",
    "name": "Hibtol"
  },
  {
    "link": "https://dawaai.pk/medicine/hibtol-1-35242.html",
    "name": "Hibtol"
  },
  {
    "link": "https://dawaai.pk/medicine/hugon-35245.html",
    "name": "Hugon"
  },
  {
    "link": "https://dawaai.pk/medicine/haricam-35615.html",
    "name": "Haricam"
  },
  {
    "link": "https://dawaai.pk/medicine/haricam-1-35616.html",
    "name": "Haricam"
  },
  {
    "link": "https://dawaai.pk/medicine/healcam-35617.html",
    "name": "Healcam"
  },
  {
    "link": "https://dawaai.pk/medicine/healcam-1-35618.html",
    "name": "Healcam"
  },
  {
    "link": "https://dawaai.pk/medicine/heldene-36034.html",
    "name": "Heldene"
  },
  {
    "link": "https://dawaai.pk/medicine/hocam-36035.html",
    "name": "Hocam"
  },
  {
    "link": "https://dawaai.pk/medicine/hydrogen-peroxide-450ml-37570.html",
    "name": "Hydrogen Peroxide 450ml"
  },
  {
    "link": "https://dawaai.pk/medicine/hisalz-40gm-37897.html",
    "name": "Hisalz"
  },
  {
    "link": "https://dawaai.pk/medicine/hydralazine-1-40037.html",
    "name": "Hydralazine HCL"
  },
  {
    "link": "https://dawaai.pk/medicine/hefmic-6-40246.html",
    "name": "Hefmic"
  },
  {
    "link": "https://dawaai.pk/medicine/hepmol-7-40542.html",
    "name": "Hepmol"
  },
  {
    "link": "https://dawaai.pk/medicine/hi-salz-43195.html",
    "name": "Hi-Salz Double Action Power Toothpaste 40gm"
  }
]